docs/__init__.py
docs/genome_comparison_scripts/__init__.py
docs/genome_comparison_scripts/karyogram_plotting_utility.py
docs/genome_comparison_scripts/plot_genetic_hdbscan.py
docs/genome_comparison_scripts/plot_rules.py
docs/genome_comparison_scripts/plot_rules_repeats.py
polycracker/__init__.py
polycracker/polycracker.py
polycracker/venn.py
polycracker-1.0.3.dist-info/LICENSE
polycracker-1.0.3.dist-info/METADATA
polycracker-1.0.3.dist-info/WHEEL
polycracker-1.0.3.dist-info/entry_points.txt
polycracker-1.0.3.dist-info/top_level.txt
polycracker-1.0.3.dist-info/RECORD
