Metadata-Version: 2.1
Name: polycracker
Version: 1.0.3
Summary: unsupervised classification of polyploid subgenomes
Home-page: https://bitbucket.org/berkeleylab/jgi-polycracker
Author: polycracker team
Author-email: sgordon@lbl.gov
License: MIT
Platform: UNKNOWN
Classifier: License :: OSI Approved :: MIT License
Classifier: Programming Language :: Python :: 2
Classifier: Programming Language :: Python :: 2.7
